hyped/__init__.py
hyped/cli.py
hyped/datasets/__init__.py
hyped/datasets/cas.py
hyped/datasets/xcr.py
hyped/stages/__init__.py
hyped/stages/prepare/__init__.py
hyped/stages/prepare/__main__.py
hyped/stages/prepare/auto.py
hyped/stages/prepare/main.py
hyped/stages/prepare/pipeline.py
hyped/stages/prepare/filters/__init__.py
hyped/stages/prepare/filters/base.py
hyped/stages/prepare/filters/msl.py
hyped/stages/prepare/processors/__init__.py
hyped/stages/prepare/processors/base.py
hyped/stages/prepare/processors/bio.py
hyped/stages/prepare/processors/tokenizer.py
hyped/stages/test/__init__.py
hyped/stages/test/__main__.py
hyped/stages/test/main.py
hyped/stages/train/__init__.py
hyped/stages/train/__main__.py
hyped/stages/train/main.py
hyped/stages/train/metrics/__init__.py
hyped/stages/train/metrics/auto.py
hyped/stages/train/metrics/collection.py
hyped/stages/train/metrics/processors.py
hyped/stages/train/metrics/metrics/__init__.py
hyped/stages/train/metrics/metrics/base.py
hyped/stages/train/metrics/metrics/cls.py
hyped/stages/train/metrics/metrics/mlc.py
hyped/stages/train/metrics/metrics/seqeval.py
hyped/stages/train/modeling/__init__.py
hyped/stages/train/modeling/auto.py
hyped/stages/train/modeling/collator.py
hyped/stages/train/modeling/trainer.py
hyped/stages/train/modeling/wrapper.py
hyped/stages/train/modeling/heads/__init__.py
hyped/stages/train/modeling/heads/base.py
hyped/stages/train/modeling/heads/causal_lm.py
hyped/stages/train/modeling/heads/cls.py
hyped/stages/train/modeling/heads/mlc.py
hyped/stages/train/modeling/heads/tagging.py
hyped/utils/__init__.py
hyped/utils/typedlist.py
hyped/utils/typedmapping.py
hyped-0.0.5.dist-info/LICENSE
hyped-0.0.5.dist-info/METADATA
hyped-0.0.5.dist-info/WHEEL
hyped-0.0.5.dist-info/entry_points.txt
hyped-0.0.5.dist-info/top_level.txt
hyped-0.0.5.dist-info/RECORD
