Metadata-Version: 2.1
Name: hyped
Version: 0.0.5
Summary: A collection of data pipelines to ease the training of transformer models
Home-page: https://github.com/ndoll1998/hyped/tree/master
Author: Niclas Doll
Author-email: niclas@amazonis.net
Classifier: License :: Freely Distributable
Classifier: License :: OSI Approved :: Apache Software License
Classifier: Programming Language :: Python :: 3.10
License-File: LICENSE
Requires-Dist: adapter-transformers (>=3.2.1)
Requires-Dist: datasets (>=2.12.0)
Requires-Dist: evaluate (>=0.4.0)
Requires-Dist: torch (>=2.0.0)
Requires-Dist: pydantic (>=1.10.7)
